ankamantatra/__init__.py
ankamantatra/__main__.py
ankamantatra/commands/__init__.py
ankamantatra/commands/list_questions.py
ankamantatra/commands/play_quizz.py
ankamantatra/data.json
ankamantatra/models/__init__.py
ankamantatra/models/category.py
ankamantatra/models/question.py
ankamantatra/models/type.py
ankamantatra/utils.py
ankamantatra-1.0.0.dist-info/entry_points.txt
ankamantatra-1.0.0.dist-info/LICENSE
ankamantatra-1.0.0.dist-info/WHEEL
ankamantatra-1.0.0.dist-info/METADATA
ankamantatra-1.0.0.dist-info/RECORD
