Metadata-Version: 2.1
Name: ankamantatra
Version: 1.0.0
Summary: A simple CLI quizz game
Author: Tsierenana Bôtramanagna Gracy
Author-email: gtsierenana@gmail.com
Requires-Python: >=3.8,<4.0
Classifier: Programming Language :: Python :: 3
Classifier: Programming Language :: Python :: 3.8
Classifier: Programming Language :: Python :: 3.9
Classifier: Programming Language :: Python :: 3.10
Requires-Dist: click (>=8.1.3,<9.0.0)
Requires-Dist: click-help-colors (>=0.9.1,<0.10.0)
